spl_widgets/__init__.py
spl_widgets/__main__.py
spl_widgets/batch_tune.py
spl_widgets/gorilla_clean.py
spl_widgets/jukemake.py
spl_widgets/misc_util.py
spl_widgets/stk_swx.py
spl_widgets/tune_freq.py
spl_widgets/tuner.py
spl_widgets/autoscorer/autoscore.py
spl_widgets/autoscorer/autoscorer_gui.py
spl_widgets/autoscorer/tokenize_to_ipa.py
spl_widgets/data/cmudict.sqlite
spl_widgets/data/help_text.json
spl_widgets/util/color_util.py
spl_widgets/util/gui_util.py
spl_widgets/util/sqlite_db.py
spl_widgets-1.8.1.dist-info/LICENSE
spl_widgets-1.8.1.dist-info/METADATA
spl_widgets-1.8.1.dist-info/WHEEL
spl_widgets-1.8.1.dist-info/entry_points.txt
spl_widgets-1.8.1.dist-info/top_level.txt
spl_widgets-1.8.1.dist-info/RECORD
