Metadata-Version: 2.1
Name: spl_widgets
Version: 1.8.1
Summary: Widgets for the Barnard Speech Perception Laboratory
Home-page: https://github.com/clntsf/spl_widgets
Author: Colin Simon-Fellowes
Author-email: colin.tsf@gmail.com
Classifier: Programming Language :: Python :: 3
Classifier: License :: OSI Approved :: MIT License
Classifier: Operating System :: MacOS
Requires-Python: >=3.8
License-File: LICENSE
Requires-Dist: pandas
Requires-Dist: tkinterdnd2-universal
Requires-Dist: openpyxl
Requires-Dist: lxml
